switchgrid_python_client/__init__.py
switchgrid_python_client-0.1.4.dist-info/METADATA
switchgrid_python_client-0.1.4.dist-info/WHEEL
switchgrid_python_client-0.1.4.dist-info/RECORD
